{
    "comment": {
        "comment": "这剧里多一个正常点的人我都不给他五星。",
        "id": "3210151163",
        "user": {
            "kind": "user",
            "name": "悠南",
            "url": "https://www.douban.com/people/141721907/",
            "uri": "douban://douban.com/user/141721907",
            "avatar": "https://img3.doubanio.com/icon/up141721907-2.jpg",
            "is_club": false,
            "type": "user",
            "id": "141721907",
            "uid": "141721907"
        }
    },
    "rating": {
        "count": 45175,
        "max": 10,
        "star_count": 4.5,
        "value": 8.7
    },
    "vendor_count": 0,
    "playable_date": null,
    "pic": {
        "large": "https://img1.doubanio.com/view/photo/m_ratio_poster/public/p2759888858.jpg",
        "normal": "https://img1.doubanio.com/view/photo/s_ratio_poster/public/p2759888858.jpg"
    },
    "honor_infos": [
        {
            "kind": "tv",
            "uri": "douban://douban.com/subject_collection/ECHU473PI?type=rank&category=movie&rank_type=tv_genre",
            "rank": 9,
            "title": "奇幻类美剧榜"
        }
    ],
    "vendor_icons": [],
    "year": "2022",
    "card_subtitle": "2022 / 美国 / 喜剧 动作 科幻 犯罪 奇幻 冒险 / 詹姆斯·古恩 罗斯玛丽·罗德里格兹 布拉德·安德森 / 约翰·塞纳 丹妮尔·布鲁克斯",
    "id": "35209701",
    "title": "和平使者 第一季",
    "tags": [
        {
            "name": "奇幻类美剧榜",
            "uri": "douban://douban.com/subject_collection/ECHU473PI?category=movie&rank_type=tv_genre&type=rank"
        },
        {
            "name": "喜欢《辐射 第一季》的也喜欢",
            "uri": "douban://douban.com/tv/recommend_tag?type=like_like&id=35128081"
        },
        {
            "name": "美国 喜剧 科幻",
            "uri": "douban://douban.com/tv/recommend_tag?tag=%E7%BE%8E%E5%9B%BD%2C%E5%96%9C%E5%89%A7%2C%E7%A7%91%E5%B9%BB&type=tags"
        }
    ],
    "interest": null,
    "type": "tv",
    "alg_json": "{\"reason_data\":[[\"like_like\",\"35128081\",{}],[\"tag_descr\",null,{\"tags\":[\"美国\",\"喜剧\",\"科幻\"]}]],\"card_type\":\"tv\",\"UGROUP\":\"baseline\",\"id\":\"35209701\",\"alg_strategy\":\"user_tv\"}",
    "has_linewatch": false,
    "photos": [
        "https://img9.doubanio.com/view/photo/m/public/p2856994525.jpg",
        "https://img1.doubanio.com/view/photo/m/public/p2844480790.jpg",
        "https://img2.doubanio.com/view/photo/m/public/p2856995341.jpg",
        "https://img1.doubanio.com/view/photo/m/public/p2856994589.jpg"
    ],
    "card": "subject",
    "playable_date_info": "",
    "following_rating": null,
    "uri": "douban://douban.com/tv/35209701",
    "episodes_info": "",
    "item_type": "tv"
}